ai.py
ai_prompt-0.0.1.dist-info/LICENSE
ai_prompt-0.0.1.dist-info/METADATA
ai_prompt-0.0.1.dist-info/WHEEL
ai_prompt-0.0.1.dist-info/entry_points.txt
ai_prompt-0.0.1.dist-info/top_level.txt
ai_prompt-0.0.1.dist-info/RECORD
