Metadata-Version: 2.1
Name: ai-prompt
Version: 0.0.1
Summary: An Ai for command line
Author: hasan
Author-email: hasanfq818@gmail.com
License: MIT
Classifier: Programming Language :: Python :: 3
Classifier: License :: OSI Approved :: MIT License
Classifier: Operating System :: OS Independent
Requires-Python: >=3.6
License-File: LICENSE
Requires-Dist: requests ==2.32.3
Requires-Dist: prompt-toolkit ==3.0.43
